{"metadata": {"last_updated": "2026-07-23", "sources": ["Baseball Almanac", "Baseball-Reference", "SABR Lahman", "Baseball Data Hub"], "coverage": "1876-2025 NL seasons"}, "eras": {"founding_1876_1900": {"name": "Founding Era", "start_year": 1876, "end_year": 1900, "games_per_season": "60-112", "dominant_team": "Boston (5 pennants)", "key_teams": ["Boston (5)", "Chicago (4)", "Providence (3)", "Baltimore (3)"], "num_teams": "8", "total_pennants_awarded": 25, "era_notes": "NL founded 1876; teams folded and relocated; no World Series until 1903", "franchises_surviving": ["Boston (became Atlanta Braves)", "Chicago (Cubs)", "Cincinnati Reds", "Pittsburgh Pirates", "Philadelphia Phillies"]}, "dead_ball_1901_1920": {"name": "Dead Ball Era", "start_year": 1901, "end_year": 1920, "games_per_season": 154, "dominant_team": "New York Giants (6 pennants)", "key_teams": ["NY Giants (6)", "Chicago Cubs (4)", "Pittsburgh Pirates (2)", "Boston Braves (1)", "Brooklyn Superbas (2)"], "num_teams": "8", "total_pennants_awarded": 20, "era_notes": "World Series begins 1903; 1906 Cubs set 116-win record; Miracle Braves 1914; first Brooklyn pennant", "notable_records": ["1906 Cubs: 116 wins (NL record)", "1909 Pirates: 110 wins", "1914 Braves: 94-59 (last to first)"]}, "live_ball_1921_1940": {"name": "Live Ball Era", "start_year": 1921, "end_year": 1940, "games_per_season": 154, "dominant_team": "St. Louis Cardinals (5 pennants)", "key_teams": ["Cardinals (5)", "NY Giants (4)", "Chicago Cubs (3)", "Pittsburgh Pirates (2)", "Brooklyn Robins (1)"], "num_teams": "8", "total_pennants_awarded": 20, "era_notes": "Cardinals dynasty begins; franchise migrations; Gashouse Gang 1934", "notable_records": ["1931 Cardinals: 101-53", "1934 Cardinals: Gas House Gang", "1935 Cubs: 1112 runs scored (NL record)"]}, "post_war_1941_1960": {"name": "Post-War Era", "start_year": 1941, "end_year": 1960, "games_per_season": 154, "dominant_team": "St. Louis Cardinals (9 pennants)", "key_teams": ["Cardinals (9)", "Dodgers (3)", "NY Giants (2)", "Braves (2)", "Reds (1)", "Pirates (2)"], "num_teams": "8 to 10", "total_pennants_awarded": 20, "era_notes": "Cardinals greatest dynasty (9 pennants, 20 years); Dodgers-Giants rivalry peaks; franchise relocations (Brooklyn-LA 1958, NY Giants-SF 1958); 1951 Shot Heard Round the World", "notable_records": ["1943 Cardinals: 105-49", "1954 Giants: 97-57", "1959 Dodgers: first LA pennant"]}, "expansion_1961_1980": {"name": "Expansion Era", "start_year": 1961, "end_year": 1980, "games_per_season": 162, "dominant_team": "LA Dodgers (5 pennants)", "key_teams": ["LA Dodgers (5)", "Cincinnati Reds (3)", "Cardinals (2)", "NY Mets (1)", "Pirates (2)", "Astros (1)"], "num_teams": "10 to 12", "total_pennants_awarded": 20, "era_notes": "162-game season begins 1962; NL expands to 10 (1962) then 12 (1969); Miracle Mets 1969; Big Red Machine 1975-76", "notable_records": ["1962 Mets: 40-120 (most NL losses modern era)", "1969 Mets: 100-62 (Miracle Mets)", "1975-76 Reds: Back-to-back WS", "1979 Pirates: 98-64 WS (We Are Family)"]}, "divisional_play_1981_2000": {"name": "Divisional Play Era", "start_year": 1981, "end_year": 2000, "games_per_season": 162, "dominant_team": "Atlanta Braves (14 consecutive division titles 1991-2005)", "key_teams": ["Atlanta Braves (14 div titles)", "Cincinnati Reds (3 pennants)", "LA Dodgers (4 pennants)", "Cardinals (1 pennant)", "Marlins (2 WS titles)"], "num_teams": "12", "total_pennants_awarded": 20, "era_notes": "Three-division format with Wild Card (1994); Braves dynasty unprecedented; 1994 strike cancels season; Marlins win 2 WS titles", "notable_records": ["1994: Season cancelled, no WS", "1998 Braves: 106-56 (most NL wins)", "2001 D-backs: WS winners in 4th season as expansion team"]}, "modern_era_2001_2025": {"name": "Modern Era", "start_year": 2001, "end_year": 2025, "games_per_season": 162, "dominant_team": "LA Dodgers (3 pennants, 8 straight NL West)", "key_teams": ["LA Dodgers (3 pennants, 8 div)", "Cardinals (3 pennants)", "Giants (3 pennants, 3 WS)", "Braves (1 pennant, 2021 WS)", "D-backs (1 pennant, 2001 WS)"], "num_teams": "15", "total_pennants_awarded": 25, "era_notes": "NL competitive balance shifts; Cardinals resurgence 2000s; Giants 3 WS titles 2010-2014; Cubs break 108-year drought 2016; Dodgers modern dynasty 2013-2025", "notable_records": ["2020 Dodgers: .717 win pct (COVID 60-game)", "2022 Phillies: 10 consecutive postseason wins", "2023 Braves: 104 wins (most across all leagues)", "2025 Dodgers: 3rd WS in 4 years (9th title)"]}}, "league_wide_trends": {"winning_percentage_rankings_through_2025": [{"team": "San Francisco Giants", "win_pct": 0.535}, {"team": "San Diego Padres", "win_pct": 0.534}, {"team": "Los Angeles Dodgers", "win_pct": 0.532}, {"team": "Milwaukee Brewers", "win_pct": 0.503}, {"team": "St. Louis Cardinals", "win_pct": 0.513}, {"team": "Chicago Cubs", "win_pct": 0.513}, {"team": "Atlanta Braves", "win_pct": 0.504}, {"team": "Pittsburgh Pirates", "win_pct": 0.501}, {"team": "Cincinnati Reds", "win_pct": 0.5}, {"team": "Colorado Rockies", "win_pct": 0.505}, {"team": "New York Mets", "win_pct": 0.483}, {"team": "Arizona Diamondbacks", "win_pct": 0.489}, {"team": "Washington Nationals", "win_pct": 0.482}, {"team": "Philadelphia Phillies", "win_pct": 0.475}, {"team": "Miami Marlins", "win_pct": 0.462}]}}